pydynamodb/__init__.py
pydynamodb/common.py
pydynamodb/connection.py
pydynamodb/converter.py
pydynamodb/cursor.py
pydynamodb/error.py
pydynamodb/executor.py
pydynamodb/model.py
pydynamodb/result_set.py
pydynamodb/util.py
pydynamodb/sql/__init__.py
pydynamodb/sql/base.py
pydynamodb/sql/common.py
pydynamodb/sql/ddl_alter.py
pydynamodb/sql/ddl_create.py
pydynamodb/sql/ddl_drop.py
pydynamodb/sql/ddl_sql.py
pydynamodb/sql/dml_delete.py
pydynamodb/sql/dml_insert.py
pydynamodb/sql/dml_select.py
pydynamodb/sql/dml_sql.py
pydynamodb/sql/dml_update.py
pydynamodb/sql/json_parser.py
pydynamodb/sql/parser.py
pydynamodb/sql/util.py
pydynamodb/sql/util_sql.py
pydynamodb/sqlalchemy_dynamodb/__init__.py
pydynamodb/sqlalchemy_dynamodb/pydynamodb.py
pydynamodb/superset_dynamodb/__init__.py
pydynamodb/superset_dynamodb/dml_select.py
pydynamodb/superset_dynamodb/helper.py
pydynamodb/superset_dynamodb/pydynamodb.py
pydynamodb/superset_dynamodb/querydb.py
pydynamodb/superset_dynamodb/querydb_sqlite.py
pydynamodb-0.8.1.dist-info/licenses/LICENSE
pydynamodb-0.8.1.dist-info/METADATA
pydynamodb-0.8.1.dist-info/WHEEL
pydynamodb-0.8.1.dist-info/entry_points.txt
pydynamodb-0.8.1.dist-info/top_level.txt
pydynamodb-0.8.1.dist-info/RECORD
