Metadata-Version: 2.4
Name: pydynamodb
Version: 0.8.1
Summary: Python DB API 2.0 (PEP 249) client for Amazon DynamoDB
Home-page: https://github.com/passren/PyDynamoDB
Author: Peng Ren
Author-email: passren9099@hotmail.com
License: MIT
Project-URL: Documentation, https://github.com/passren/PyDynamoDB/wiki
Project-URL: Source, https://github.com/passren/PyDynamoDB
Project-URL: Tracker, https://github.com/passren/PyDynamoDB/issues
Keywords: DB-API Amazon AWS DynamoDB
Classifier: Development Status :: 5 - Production/Stable
Classifier: Intended Audience :: Developers
Classifier: Programming Language :: Python
Classifier: Programming Language :: Python
Classifier: Programming Language :: Python :: 3.9
Classifier: Programming Language :: Python :: 3.10
Classifier: Programming Language :: Python :: 3.11
Classifier: Programming Language :: Python :: 3.12
Classifier: Programming Language :: Python :: 3.13
Classifier: Programming Language :: Python :: 3.14
Classifier: Operating System :: OS Independent
Classifier: License :: OSI Approved :: MIT License
Requires-Python: >=3.9
License-File: LICENSE
Requires-Dist: boto3>=1.21.0
Requires-Dist: botocore>=1.24.7
Requires-Dist: tenacity>=4.1.0
Requires-Dist: pyparsing>=3.0.0
Provides-Extra: sqlalchemy
Requires-Dist: sqlalchemy>=1.0.0; extra == "sqlalchemy"
Provides-Extra: sqlean
Requires-Dist: sqlean.py>=3.45.0; extra == "sqlean"
Dynamic: author
Dynamic: author-email
Dynamic: classifier
Dynamic: description
Dynamic: description-content-type
Dynamic: home-page
Dynamic: keywords
Dynamic: license
Dynamic: license-file
Dynamic: project-url
Dynamic: provides-extra
Dynamic: requires-dist
Dynamic: requires-python
Dynamic: summary
